{
  "channel_name": "Animal Planet Hindi",
  "date": "December 08, 2025",
  "schedule": [
    {
      "show_name": "Wild Assassins",
      "start_time": "12:00 AM",
      "end_time": "12:31 AM",
      "show_logo": "https://jiotv.catchup.cdn.jio.com/dare_images/shows/2025-12-08/251208566000.jpg"
    },
    {
      "show_name": "Cheetah Blood Brothers",
      "start_time": "12:31 AM",
      "end_time": "1:31 AM",
      "show_logo": "https://jiotv.catchup.cdn.jio.com/dare_images/shows/2025-12-08/251208566001.jpg"
    },
    {
      "show_name": "Parenthood",
      "start_time": "1:31 AM",
      "end_time": "2:24 AM",
      "show_logo": "https://jiotv.catchup.cdn.jio.com/dare_images/shows/2025-12-08/251208566002.jpg"
    },
    {
      "show_name": "Africa's Trees of Life",
      "start_time": "2:24 AM",
      "end_time": "3:25 AM",
      "show_logo": "https://jiotv.catchup.cdn.jio.com/dare_images/shows/2025-12-08/251208566003.jpg"
    },
    {
      "show_name": "The Lions Rule",
      "start_time": "3:25 AM",
      "end_time": "4:25 AM",
      "show_logo": "https://jiotv.catchup.cdn.jio.com/dare_images/shows/2025-12-08/251208566004.jpg"
    },
    {
      "show_name": "Cheetah: Against All Odds",
      "start_time": "4:25 AM",
      "end_time": "5:11 AM",
      "show_logo": "https://jiotv.catchup.cdn.jio.com/dare_images/shows/2025-12-08/251208566005.jpg"
    },
    {
      "show_name": "Africa's Hunters",
      "start_time": "5:11 AM",
      "end_time": "6:00 AM",
      "show_logo": "https://jiotv.catchup.cdn.jio.com/dare_images/shows/2025-12-08/251208566006.jpg"
    },
    {
      "show_name": "Wild Africa: Rivers of Life",
      "start_time": "6:00 AM",
      "end_time": "7:00 AM",
      "show_logo": "https://jiotv.catchup.cdn.jio.com/dare_images/shows/2025-12-08/251208566007.jpg"
    },
    {
      "show_name": "Islands: Nature's Wild Laboratories",
      "start_time": "7:00 AM",
      "end_time": "7:44 AM",
      "show_logo": "https://jiotv.catchup.cdn.jio.com/dare_images/shows/2025-12-08/251208566008.jpg"
    },
    {
      "show_name": "Tiger Legacy",
      "start_time": "7:44 AM",
      "end_time": "8:34 AM",
      "show_logo": "https://jiotv.catchup.cdn.jio.com/dare_images/shows/2025-12-08/251208566009.jpg"
    },
    {
      "show_name": "Wildest Survival",
      "start_time": "8:34 AM",
      "end_time": "9:25 AM",
      "show_logo": "https://jiotv.catchup.cdn.jio.com/dare_images/shows/2025-12-08/251208566010.jpg"
    },
    {
      "show_name": "The Leopardess",
      "start_time": "9:25 AM",
      "end_time": "10:17 AM",
      "show_logo": "https://jiotv.catchup.cdn.jio.com/dare_images/shows/2025-12-08/251208566011.jpg"
    },
    {
      "show_name": "Epic Animal Encounters",
      "start_time": "10:17 AM",
      "end_time": "10:44 AM",
      "show_logo": "https://jiotv.catchup.cdn.jio.com/dare_images/shows/2025-12-08/251208566012.jpg"
    },
    {
      "show_name": "Jungle Planet",
      "start_time": "10:44 AM",
      "end_time": "11:12 AM",
      "show_logo": "https://jiotv.catchup.cdn.jio.com/dare_images/shows/2025-12-08/251208566013.jpg"
    },
    {
      "show_name": "Hippo Supremacy",
      "start_time": "11:12 AM",
      "end_time": "12:05 PM",
      "show_logo": "https://jiotv.catchup.cdn.jio.com/dare_images/shows/2025-12-08/251208566014.jpg"
    },
    {
      "show_name": "Epic Animal Encounters",
      "start_time": "12:05 PM",
      "end_time": "12:32 PM",
      "show_logo": "https://jiotv.catchup.cdn.jio.com/dare_images/shows/2025-12-08/251208566015.jpg"
    },
    {
      "show_name": "Jungle Planet",
      "start_time": "12:32 PM",
      "end_time": "1:00 PM",
      "show_logo": "https://jiotv.catchup.cdn.jio.com/dare_images/shows/2025-12-08/251208566016.jpg"
    },
    {
      "show_name": "Africa's Hunters",
      "start_time": "1:00 PM",
      "end_time": "1:52 PM",
      "show_logo": "https://jiotv.catchup.cdn.jio.com/dare_images/shows/2025-12-08/251208566017.jpg"
    },
    {
      "show_name": "Nature's Ultimate Survivors",
      "start_time": "1:52 PM",
      "end_time": "2:44 PM",
      "show_logo": "https://jiotv.catchup.cdn.jio.com/dare_images/shows/2025-12-08/251208566018.jpg"
    },
    {
      "show_name": "Bastion of the Giants",
      "start_time": "2:44 PM",
      "end_time": "3:42 PM",
      "show_logo": "https://jiotv.catchup.cdn.jio.com/dare_images/shows/2025-12-08/251208566019.jpg"
    },
    {
      "show_name": "The Lions Rule",
      "start_time": "3:42 PM",
      "end_time": "4:38 PM",
      "show_logo": "https://jiotv.catchup.cdn.jio.com/dare_images/shows/2025-12-08/251208566020.jpg"
    },
    {
      "show_name": "Extreme Africa",
      "start_time": "4:38 PM",
      "end_time": "5:29 PM",
      "show_logo": "https://jiotv.catchup.cdn.jio.com/dare_images/shows/2025-12-08/251208566021.jpg"
    },
    {
      "show_name": "The wild West: a prairie dog's life",
      "start_time": "5:29 PM",
      "end_time": "6:21 PM",
      "show_logo": "https://jiotv.catchup.cdn.jio.com/dare_images/shows/2025-12-08/251208566022.jpg"
    },
    {
      "show_name": "Tiger Legacy",
      "start_time": "6:21 PM",
      "end_time": "7:14 PM",
      "show_logo": "https://jiotv.catchup.cdn.jio.com/dare_images/shows/2025-12-08/251208566023.jpg"
    },
    {
      "show_name": "Lioness in Exile",
      "start_time": "7:14 PM",
      "end_time": "8:11 PM",
      "show_logo": "https://jiotv.catchup.cdn.jio.com/dare_images/shows/2025-12-08/251208566024.jpg"
    },
    {
      "show_name": "Africa's Hunters",
      "start_time": "8:11 PM",
      "end_time": "9:06 PM",
      "show_logo": "https://jiotv.catchup.cdn.jio.com/dare_images/shows/2025-12-08/251208566025.jpg"
    },
    {
      "show_name": "Wild Africa: Rivers of Life",
      "start_time": "9:06 PM",
      "end_time": "10:03 PM",
      "show_logo": "https://jiotv.catchup.cdn.jio.com/dare_images/shows/2025-12-08/251208566026.jpg"
    },
    {
      "show_name": "Africa's Super Snake",
      "start_time": "10:03 PM",
      "end_time": "10:55 PM",
      "show_logo": "https://jiotv.catchup.cdn.jio.com/dare_images/shows/2025-12-08/251208566027.jpg"
    },
    {
      "show_name": "Africa's Hunters",
      "start_time": "10:55 PM",
      "end_time": "11:46 PM",
      "show_logo": "https://jiotv.catchup.cdn.jio.com/dare_images/shows/2025-12-08/251208566028.jpg"
    },
    {
      "show_name": "Africa's Hunters",
      "start_time": "11:46 PM",
      "end_time": "11:59 PM",
      "show_logo": "https://jiotv.catchup.cdn.jio.com/dare_images/shows/2025-12-08/251208566029.jpg"
    }
  ]
}