{
  "channel_name": "Kolkata TV",
  "date": "December 09, 2025",
  "schedule": [
    {
      "show_name": "Chaturtho Stamva",
      "start_time": "12:00 AM",
      "end_time": "12:30 AM",
      "show_logo": "https://dtil.tmsimg.com/assets/p28935255_b_h9_aa.jpg?lock=880x660"
    },
    {
      "show_name": "Bharat Amar Bharatborsha",
      "start_time": "12:30 AM",
      "end_time": "01:00 AM",
      "show_logo": "https://dtil.tmsimg.com/assets/p28935266_b_h9_aa.jpg?lock=880x660"
    },
    {
      "show_name": "Sangbad Saradin",
      "start_time": "01:00 AM",
      "end_time": "06:00 AM",
      "show_logo": "https://dtil.tmsimg.com/assets/p28935283_b_h9_aa.jpg?lock=880x660"
    },
    {
      "show_name": "Sangbad Saradin",
      "start_time": "06:00 AM",
      "end_time": "07:00 AM",
      "show_logo": "https://dtil.tmsimg.com/assets/p28935283_b_h9_aa.jpg?lock=880x660"
    },
    {
      "show_name": "Bharat Amar Bharatborsha",
      "start_time": "07:00 AM",
      "end_time": "07:30 AM",
      "show_logo": "https://dtil.tmsimg.com/assets/p28935266_b_h9_aa.jpg?lock=880x660"
    },
    {
      "show_name": "Amar Sahar",
      "start_time": "07:30 AM",
      "end_time": "07:32 AM",
      "show_logo": "https://dtil.tmsimg.com/assets/p28935367_b_h9_aa.jpg?lock=880x660"
    },
    {
      "show_name": "Politics",
      "start_time": "07:32 AM",
      "end_time": "07:57 AM",
      "show_logo": "https://dtil.tmsimg.com/assets/p9025402_b_h9_ae.jpg?lock=880x660"
    },
    {
      "show_name": "HDL + Good Morning Kolkata",
      "start_time": "07:57 AM",
      "end_time": "08:30 AM",
      "show_logo": "https://dtil.tmsimg.com/assets/p28935381_b_h9_aa.jpg?lock=880x660"
    },
    {
      "show_name": "Chaturtho Stamva",
      "start_time": "08:30 AM",
      "end_time": "08:47 AM",
      "show_logo": "https://dtil.tmsimg.com/assets/p28935255_b_h9_aa.jpg?lock=880x660"
    },
    {
      "show_name": "AJKE",
      "start_time": "08:47 AM",
      "end_time": "08:57 AM",
      "show_logo": "https://dtil.tmsimg.com/assets/p28935621_b_h9_aa.jpg?lock=880x660"
    },
    {
      "show_name": "HDL + Sangbad Saradin",
      "start_time": "08:57 AM",
      "end_time": "09:30 AM",
      "show_logo": "https://dtil.tmsimg.com/assets/p28935395_b_h9_aa.jpg?lock=880x660"
    },
    {
      "show_name": "Amar Sahar",
      "start_time": "09:30 AM",
      "end_time": "09:32 AM",
      "show_logo": "https://dtil.tmsimg.com/assets/p28935367_b_h9_aa.jpg?lock=880x660"
    },
    {
      "show_name": "Sangbad Saradin",
      "start_time": "09:32 AM",
      "end_time": "09:59 AM",
      "show_logo": "https://dtil.tmsimg.com/assets/p28935283_b_h9_aa.jpg?lock=880x660"
    },
    {
      "show_name": "HDL + Sangbad Saradin",
      "start_time": "09:59 AM",
      "end_time": "10:59 AM",
      "show_logo": "https://dtil.tmsimg.com/assets/p28935395_b_h9_aa.jpg?lock=880x660"
    },
    {
      "show_name": "HDL + Sangbad Saradin",
      "start_time": "10:59 AM",
      "end_time": "11:30 AM",
      "show_logo": "https://dtil.tmsimg.com/assets/p28935395_b_h9_aa.jpg?lock=880x660"
    },
    {
      "show_name": "Amar Sahar",
      "start_time": "11:30 AM",
      "end_time": "11:32 AM",
      "show_logo": "https://dtil.tmsimg.com/assets/p28935367_b_h9_aa.jpg?lock=880x660"
    },
    {
      "show_name": "Sangbad Saradin",
      "start_time": "11:32 AM",
      "end_time": "11:50 AM",
      "show_logo": "https://dtil.tmsimg.com/assets/p28935283_b_h9_aa.jpg?lock=880x660"
    },
    {
      "show_name": "Bangla Ekhon",
      "start_time": "11:50 AM",
      "end_time": "11:59 AM",
      "show_logo": "https://dtil.tmsimg.com/assets/p28935426_b_h9_aa.jpg?lock=880x660"
    },
    {
      "show_name": "HDL + Aro Baro",
      "start_time": "11:59 AM",
      "end_time": "12:54 PM",
      "show_logo": "https://dtil.tmsimg.com/assets/p28935439_b_h9_aa.jpg?lock=880x660"
    },
    {
      "show_name": "5 Minute E 25",
      "start_time": "12:54 PM",
      "end_time": "12:59 PM",
      "show_logo": "https://dtil.tmsimg.com/assets/p28935459_b_h9_ab.jpg?lock=880x660"
    },
    {
      "show_name": "HDL + Sangbad Saradin",
      "start_time": "12:59 PM",
      "end_time": "01:30 PM",
      "show_logo": "https://dtil.tmsimg.com/assets/p28935395_b_h9_aa.jpg?lock=880x660"
    },
    {
      "show_name": "Amar Sahar",
      "start_time": "01:30 PM",
      "end_time": "01:32 PM",
      "show_logo": "https://dtil.tmsimg.com/assets/p28935367_b_h9_aa.jpg?lock=880x660"
    },
    {
      "show_name": "Sangbad Saradin",
      "start_time": "01:32 PM",
      "end_time": "01:50 PM",
      "show_logo": "https://dtil.tmsimg.com/assets/p28935283_b_h9_aa.jpg?lock=880x660"
    },
    {
      "show_name": "Bangla Ekhon",
      "start_time": "01:50 PM",
      "end_time": "01:59 PM",
      "show_logo": "https://dtil.tmsimg.com/assets/p28935426_b_h9_aa.jpg?lock=880x660"
    },
    {
      "show_name": "HDL + Sangbad Saradin",
      "start_time": "01:59 PM",
      "end_time": "02:54 PM",
      "show_logo": "https://dtil.tmsimg.com/assets/p28935395_b_h9_aa.jpg?lock=880x660"
    },
    {
      "show_name": "5 Minute E 25",
      "start_time": "02:54 PM",
      "end_time": "02:59 PM",
      "show_logo": "https://dtil.tmsimg.com/assets/p28935459_b_h9_ab.jpg?lock=880x660"
    },
    {
      "show_name": "HDL + Sangbad Saradin",
      "start_time": "02:59 PM",
      "end_time": "03:30 PM",
      "show_logo": "https://dtil.tmsimg.com/assets/p28935395_b_h9_aa.jpg?lock=880x660"
    },
    {
      "show_name": "Amar Sahar",
      "start_time": "03:30 PM",
      "end_time": "03:32 PM",
      "show_logo": "https://dtil.tmsimg.com/assets/p28935367_b_h9_aa.jpg?lock=880x660"
    },
    {
      "show_name": "Sangbad Saradin",
      "start_time": "03:32 PM",
      "end_time": "03:50 PM",
      "show_logo": "https://dtil.tmsimg.com/assets/p28935283_b_h9_aa.jpg?lock=880x660"
    },
    {
      "show_name": "Bangla Ekhon",
      "start_time": "03:50 PM",
      "end_time": "03:59 PM",
      "show_logo": "https://dtil.tmsimg.com/assets/p28935426_b_h9_aa.jpg?lock=880x660"
    },
    {
      "show_name": "HDL + 4 Tey Chardik",
      "start_time": "03:59 PM",
      "end_time": "04:59 PM",
      "show_logo": "https://dtil.tmsimg.com/assets/p28935482_b_h9_aa.jpg?lock=880x660"
    },
    {
      "show_name": "HDL + Sangbad Saradin",
      "start_time": "04:59 PM",
      "end_time": "05:30 PM",
      "show_logo": "https://dtil.tmsimg.com/assets/p28935395_b_h9_aa.jpg?lock=880x660"
    },
    {
      "show_name": "Amar Sahar",
      "start_time": "05:30 PM",
      "end_time": "05:32 PM",
      "show_logo": "https://dtil.tmsimg.com/assets/p28935367_b_h9_aa.jpg?lock=880x660"
    },
    {
      "show_name": "Sangbad Saradin",
      "start_time": "05:32 PM",
      "end_time": "05:59 PM",
      "show_logo": "https://dtil.tmsimg.com/assets/p28935283_b_h9_aa.jpg?lock=880x660"
    },
    {
      "show_name": "HDL + Jelar Saradin",
      "start_time": "05:59 PM",
      "end_time": "06:26 PM",
      "show_logo": "https://dtil.tmsimg.com/assets/p28935528_b_h9_aa.jpg?lock=880x660"
    },
    {
      "show_name": "Narod Narod",
      "start_time": "06:26 PM",
      "end_time": "06:56 PM",
      "show_logo": "https://dtil.tmsimg.com/assets/p28935557_b_h9_aa.jpg?lock=880x660"
    },
    {
      "show_name": "Bangla Bolchhe",
      "start_time": "06:56 PM",
      "end_time": "08:00 PM",
      "show_logo": "https://dtil.tmsimg.com/assets/p28935570_b_h9_aa.jpg?lock=880x660"
    },
    {
      "show_name": "Sera 10",
      "start_time": "08:00 PM",
      "end_time": "08:30 PM",
      "show_logo": "https://dtil.tmsimg.com/assets/p28950690_b_h9_aa.jpg?lock=880x660"
    },
    {
      "show_name": "Sangbad Saradin",
      "start_time": "08:30 PM",
      "end_time": "08:50 PM",
      "show_logo": "https://dtil.tmsimg.com/assets/p28935283_b_h9_aa.jpg?lock=880x660"
    },
    {
      "show_name": "Bishoy Bidesh",
      "start_time": "08:50 PM",
      "end_time": "09:00 PM",
      "show_logo": "https://dtil.tmsimg.com/assets/p28935588_b_h9_aa.jpg?lock=880x660"
    },
    {
      "show_name": "Stadium Bulletin",
      "start_time": "09:00 PM",
      "end_time": "09:30 PM",
      "show_logo": "https://dtil.tmsimg.com/assets/p28935602_b_h9_aa.jpg?lock=880x660"
    },
    {
      "show_name": "Politics",
      "start_time": "09:30 PM",
      "end_time": "09:59 PM",
      "show_logo": "https://dtil.tmsimg.com/assets/p9025402_b_h9_ae.jpg?lock=880x660"
    },
    {
      "show_name": "Chaturtho Stamva",
      "start_time": "09:59 PM",
      "end_time": "10:20 PM",
      "show_logo": "https://dtil.tmsimg.com/assets/p28935255_b_h9_aa.jpg?lock=880x660"
    },
    {
      "show_name": "AJKE",
      "start_time": "10:20 PM",
      "end_time": "10:30 PM",
      "show_logo": "https://dtil.tmsimg.com/assets/p28935621_b_h9_aa.jpg?lock=880x660"
    },
    {
      "show_name": "Ponero Ponero Panch",
      "start_time": "10:30 PM",
      "end_time": "10:59 PM",
      "show_logo": "https://dtil.tmsimg.com/assets/p28935657_b_h9_aa.jpg?lock=880x660"
    },
    {
      "show_name": "Bangla Bolchhe",
      "start_time": "10:59 PM",
      "end_time": "11:20 PM",
      "show_logo": "https://dtil.tmsimg.com/assets/p28935570_b_h9_aa.jpg?lock=880x660"
    },
    {
      "show_name": "Bangla Bolchhe",
      "start_time": "11:20 PM",
      "end_time": "11:30 PM",
      "show_logo": "https://dtil.tmsimg.com/assets/p28935570_b_h9_aa.jpg?lock=880x660"
    },
    {
      "show_name": "Bangla Bolchhe",
      "start_time": "11:30 PM",
      "end_time": "12:00 AM",
      "show_logo": "https://dtil.tmsimg.com/assets/p28935570_b_h9_aa.jpg?lock=880x660"
    }
  ]
}